Metadata-Version: 1.1
Name: sortusing
Version: 0.0.1
Summary: helps choose a sorting algorithm
Home-page: UNKNOWN
Author: Ujjwal Sharma
Author-email: ujjwalsharma2210@gmail.com
License: MIT
Keywords: sort
Platform: UNKNOWN
Classifier: Development Status :: 5 - Production/Stable
Classifier: Intended Audience :: Education
Classifier: Operating System :: Microsoft :: Windows :: Windows 10
Classifier: License :: OSI Approved :: MIT License
Classifier: Programming Language :: Python :: 3
